simplebumpversion/main.py
simplebumpversion/core/__init__.py
simplebumpversion/core/bump_version.py
simplebumpversion/core/change_logger.py
simplebumpversion/core/config_handler.py
simplebumpversion/core/exceptions.py
simplebumpversion/core/file_handler.py
simplebumpversion/core/git_tools.py
simplebumpversion/core/parse_arguments.py
simplebumpversion-3.0.1.dist-info/licenses/LICENSE
simplebumpversion-3.0.1.dist-info/METADATA
simplebumpversion-3.0.1.dist-info/WHEEL
simplebumpversion-3.0.1.dist-info/entry_points.txt
simplebumpversion-3.0.1.dist-info/top_level.txt
simplebumpversion-3.0.1.dist-info/RECORD
