Metadata-Version: 2.4
Name: simplebumpversion
Version: 3.0.1
Summary: Bump version numbers across several files
Author: Sukhrob Ikromov
License: MIT License
Project-URL: Repository, https://github.com/Ikromov247/bump_version
Requires-Python: >=3.7
License-File: LICENSE
Requires-Dist: PyYAML>=6.0.0
Dynamic: license-file
